MANIFEST.in
setup.py
version.txt
tests/__init__.py
tests/test_notice.py
tests/test_template.py
tests/test_track.py
yyhtools/__init__.py
yyhtools/config.py
yyhtools/dt.py
yyhtools/notice.py
yyhtools/track.py
yyhtools.egg-info/PKG-INFO
yyhtools.egg-info/SOURCES.txt
yyhtools.egg-info/dependency_links.txt
yyhtools.egg-info/top_level.txt
yyhtools/email/__init__.py
yyhtools/email/e163.py
yyhtools/html/__init__.py
yyhtools/html/escape.py
yyhtools/html/template.py
yyhtools/static/base.html
yyhtools/static/error.html
yyhtools/static/stock.html