Metadata-Version: 1.0
Name: yyhtools
Version: 0.0.24
Summary: just a simple test
Home-page: UNKNOWN
Author: yyh
Author-email: 736184425@qq.com
License: UNKNOWN
Keywords: simple,test
Platform: any
